tern/__init__.py
tern/__main__.py
tern/prep.py
tern/analyze/__init__.py
tern/analyze/common.py
tern/analyze/passthrough.py
tern/analyze/default/__init__.py
tern/analyze/default/bundle.py
tern/analyze/default/collect.py
tern/analyze/default/core.py
tern/analyze/default/default_common.py
tern/analyze/default/filter.py
tern/analyze/default/command_lib/__init__.py
tern/analyze/default/command_lib/base.yml
tern/analyze/default/command_lib/command_lib.py
tern/analyze/default/command_lib/common.yml
tern/analyze/default/command_lib/snippets.yml
tern/analyze/default/container/__init__.py
tern/analyze/default/container/image.py
tern/analyze/default/container/multi_layer.py
tern/analyze/default/container/run.py
tern/analyze/default/container/single_layer.py
tern/analyze/default/debug/__init__.py
tern/analyze/default/debug/run.py
tern/analyze/default/dockerfile/__init__.py
tern/analyze/default/dockerfile/lock.py
tern/analyze/default/dockerfile/parse.py
tern/analyze/default/dockerfile/run.py
tern/analyze/default/live/__init__.py
tern/analyze/default/live/collect.py
tern/analyze/default/live/run.py
tern/classes/__init__.py
tern/classes/command.py
tern/classes/docker_image.py
tern/classes/file_data.py
tern/classes/image.py
tern/classes/image_layer.py
tern/classes/notice.py
tern/classes/notice_origin.py
tern/classes/oci_image.py
tern/classes/origins.py
tern/classes/package.py
tern/classes/template.py
tern/extensions/__init__.py
tern/extensions/executor.py
tern/extensions/cve_bin_tool/__init__.py
tern/extensions/cve_bin_tool/executor.py
tern/extensions/scancode/__init__.py
tern/extensions/scancode/executor.py
tern/formats/__init__.py
tern/formats/consumer.py
tern/formats/generator.py
tern/formats/cyclonedx/__init__.py
tern/formats/cyclonedx/cyclonedx_common.py
tern/formats/cyclonedx/cyclonedxjson/__init__.py
tern/formats/cyclonedx/cyclonedxjson/generator.py
tern/formats/cyclonedx/cyclonedxjson/image_helpers.py
tern/formats/cyclonedx/cyclonedxjson/package_helpers.py
tern-2.12.1.dist-info/AUTHORS
tern-2.12.1.dist-info/LICENSE.txt
tern-2.12.1.dist-info/METADATA
tern-2.12.1.dist-info/NOTICE.txt
tern-2.12.1.dist-info/WHEEL
tern-2.12.1.dist-info/entry_points.txt
tern-2.12.1.dist-info/pbr.json
tern-2.12.1.dist-info/top_level.txt
tern-2.12.1.dist-info/RECORD
