Metadata-Version: 2.1
Name: tern
Version: 2.12.1
Summary: An inspection tool to find the OSS compliance metadata of the packages installed in a container image.
Home-page: https://github.com/tern-tools/tern/
Author: VMware Inc
Author-email: nishak@vmware.com
License: BSD-2.0
Project-URL: Documentation, https://github.com/tern-tools/tern/tree/master/docs
Project-URL: Source Code, https://github.com/tern-tools/tern
Project-URL: Issues, https://github.com/tern-tools/tern/issues
Keywords: Distribution,Container,Cloud-Native
Classifier: Development Status :: 3 - Alpha
Classifier: Environment :: Console
Classifier: Intended Audience :: Developers
Classifier: License :: OSI Approved :: BSD License
Classifier: Natural Language :: English
Classifier: Operating System :: POSIX
Classifier: Operating System :: POSIX :: Linux
Classifier: Programming Language :: Python :: 3.6
Classifier: Programming Language :: Python :: 3.7
Classifier: Programming Language :: Python :: Implementation :: CPython
Classifier: Topic :: Software Development
License-File: LICENSE.txt
License-File: NOTICE.txt
License-File: AUTHORS
Requires-Dist: attrs (==23.1.0)
Requires-Dist: boolean-py (==4.0)
Requires-Dist: certifi (==2023.5.7)
Requires-Dist: chardet (==5.1.0)
Requires-Dist: charset-normalizer (==3.2.0)
Requires-Dist: debian-inspector (==31.0.0)
Requires-Dist: docker (==6.1.3)
Requires-Dist: dockerfile-parse (==2.0.0)
Requires-Dist: gitdb (==4.0.10)
Requires-Dist: gitpython (==3.1.32)
Requires-Dist: idna (==3.4)
Requires-Dist: license-expression (==30.1.1)
Requires-Dist: packageurl-python (==0.11.1)
Requires-Dist: packaging (==23.1)
Requires-Dist: pbr (==5.11.1)
Requires-Dist: prettytable (==3.8.0)
Requires-Dist: pyyaml (==6.0)
Requires-Dist: regex (==2023.6.3)
Requires-Dist: requests (==2.31.0)
Requires-Dist: smmap (==5.0.0)
Requires-Dist: stevedore (==5.1.0)
Requires-Dist: urllib3 (==2.0.3)
Requires-Dist: wcwidth (==0.2.6)
Requires-Dist: websocket-client (==1.6.1)
Provides-Extra: dev
Requires-Dist: bandit (>=1.6) ; extra == 'dev'
Requires-Dist: prospector (>=1.5.1) ; extra == 'dev'
Requires-Dist: tox (>=3.14) ; extra == 'dev'
